premium_calculator_pkg/__init__.py
premium_calculator_pkg/premium_calculator.py
premium_calculator_bv-0.0.3.dist-info/METADATA
premium_calculator_bv-0.0.3.dist-info/WHEEL
premium_calculator_bv-0.0.3.dist-info/licenses/LICENSE
premium_calculator_bv-0.0.3.dist-info/RECORD
