Metadata-Version: 2.4
Name: premium-calculator-bv
Version: 0.0.3
Summary: Simple library to calculate insurance premium
Project-URL: Homepage, https://github.com/pypa/sampleproject
Project-URL: Issues, https://github.com/pypa/sampleproject/issues
Author-email: Brenno Venturini <x25122070@student.ncirl.ie>
License-Expression: MIT
License-File: LICENSE
Classifier: Operating System :: OS Independent
Classifier: Programming Language :: Python :: 3
Requires-Python: >=3.9
